package com.jason.bytecode;


public class Demo1 {
}
/*
Classfile /Users/chenchen/code/code/src/main/java/com/jason/bytecode/Demo1.class
  Last modified 2018-10-14; size 203 bytes
  MD5 checksum 483c13c7edde36939ddf7e2fb7340b3f
  Compiled from "Demo1.java"
public class com.jason.bytecode.Demo1
  minor version: 0
  major version: 52
  flags: ACC_PUBLIC, ACC_SUPER
Constant pool:
   #1 = Methodref          #3.#10         // java/lang/Object."<init>":()V
   #2 = Class              #11            // com/jason/bytecode/Demo1
   #3 = Class              #12            // java/lang/Object
   #4 = Utf8               <init>
   #5 = Utf8               ()V
   #6 = Utf8               Code
   #7 = Utf8               LineNumberTable
   #8 = Utf8               SourceFile
   #9 = Utf8               Demo1.java
  #10 = NameAndType        #4:#5          // "<init>":()V
  #11 = Utf8               com/jason/bytecode/Demo1
  #12 = Utf8               java/lang/Object
{
  public com.jason.bytecode.Demo1();
    descriptor: ()V
    flags: ACC_PUBLIC
    Code:
      stack=1, locals=1, args_size=1
         0: aload_0
         1: invokespecial #1                  // Method java/lang/Object."<init>":()V
         4: return
      LineNumberTable:
        line 3: 0
}
SourceFile: "Demo1.java"
 */
